devix/__init__.py
devix/__main__.py
devix/analysis/__init__.py
devix/analysis/base_analyzer.py
devix/analysis/performance_analyzer.py
devix/analysis/project_scanner.py
devix/analysis/quality_analyzer.py
devix/analysis/security_analyzer.py
devix/analysis/test_analyzer.py
devix/cli/__init__.py
devix/cli/main.py
devix/config/__init__.py
devix/config/config_manager.py
devix/config/settings.py
devix/core/__init__.py
devix/core/orchestrator.py
devix/reporting/__init__.py
devix/reporting/base_formatter.py
devix/reporting/enhanced_generator.py
devix/reporting/markdown_formatter.py
devix/reporting/text_formatter.py
devix-2.1.8.dist-info/METADATA
devix-2.1.8.dist-info/WHEEL
devix-2.1.8.dist-info/entry_points.txt
devix-2.1.8.dist-info/licenses/LICENSE
devix-2.1.8.dist-info/RECORD
