Metadata-Version: 2.4
Name: devix
Version: 2.1.8
Summary: Automated development and code repair system with enhanced analysis capabilities
Project-URL: Homepage, https://github.com/c20frame/devix
Project-URL: Documentation, https://devix.softreck.dev
Project-URL: Repository, https://github.com/c20frame/devix
Project-URL: Issues, https://github.com/c20frame/devix/issues
Project-URL: Changelog, https://github.com/c20frame/devix/blob/main/CHANGELOG.md
Author-email: Tom Sapletta <info@softreck.dev>
License:                                  Apache License
License-File: LICENSE
Keywords: automated-development,code-analysis,code-repair,continuous-integration,monitoring,quality-assurance,testing
Classifier: Development Status :: 4 - Beta
Classifier: Intended Audience :: Developers
Classifier: License :: OSI Approved :: Apache Software License
Classifier: Programming Language :: Python :: 3
Classifier: Programming Language :: Python :: 3.8
Classifier: Programming Language :: Python :: 3.9
Classifier: Programming Language :: Python :: 3.10
Classifier: Programming Language :: Python :: 3.11
Classifier: Programming Language :: Python :: 3.12
Classifier: Topic :: Software Development :: Quality Assurance
Classifier: Topic :: Software Development :: Testing
Requires-Python: >=3.8
Requires-Dist: click>=8.0.0
Requires-Dist: colorama>=0.4.6
Requires-Dist: docker>=6.0.0
Requires-Dist: gitpython>=3.1.0
Requires-Dist: jinja2>=3.1.0
Requires-Dist: markdown>=3.4.0
Requires-Dist: pathlib2>=2.3.0
Requires-Dist: psutil>=5.9.0
Requires-Dist: pyyaml>=6.0
Requires-Dist: requests>=2.28.0
Requires-Dist: rich>=13.0.0
Requires-Dist: tabulate>=0.9.0
Requires-Dist: typing-extensions>=4.5.0
Provides-Extra: dev
Requires-Dist: bandit>=1.7.0; extra == 'dev'
Requires-Dist: black>=23.0.0; extra == 'dev'
Requires-Dist: flake8>=6.0.0; extra == 'dev'
Requires-Dist: isort>=5.12.0; extra == 'dev'
Requires-Dist: mypy>=1.0.0; extra == 'dev'
Requires-Dist: pre-commit>=3.0.0; extra == 'dev'
Requires-Dist: pylint>=2.17.0; extra == 'dev'
Requires-Dist: pytest-cov>=4.0.0; extra == 'dev'
Requires-Dist: pytest>=7.0.0; extra == 'dev'
Requires-Dist: radon>=6.0.0; extra == 'dev'
Requires-Dist: safety>=2.3.0; extra == 'dev'
Provides-Extra: docs
Requires-Dist: mkdocs-click>=0.8.0; extra == 'docs'
Requires-Dist: mkdocs-material>=9.0.0; extra == 'docs'
Requires-Dist: mkdocs>=1.4.0; extra == 'docs'
Requires-Dist: mkdocstrings[python]>=0.20.0; extra == 'docs'
Provides-Extra: test
Requires-Dist: pytest-cov>=4.0.0; extra == 'test'
Requires-Dist: pytest-mock>=3.10.0; extra == 'test'
Requires-Dist: pytest-xdist>=3.2.0; extra == 'test'
Requires-Dist: pytest>=7.0.0; extra == 'test'
